float_api/__init__.py
float_api/float_api.py
float_api-0.0.15.dist-info/LICENSE
float_api-0.0.15.dist-info/METADATA
float_api-0.0.15.dist-info/WHEEL
float_api-0.0.15.dist-info/top_level.txt
float_api-0.0.15.dist-info/RECORD
