Metadata-Version: 2.1
Name: float_api
Version: 0.0.15
Summary: A wrapper for the API at float.com
Home-page: https://github.com/tobiasbp/float_api
Author: Tobias Balle-Petersen
Author-email: tobiasbp@gmail.com
Project-URL: Bug Tracker, https://github.com/tobiasbp/float_api/issues
Keywords: Float api wrapper client
Classifier: Programming Language :: Python :: 3
Classifier: License :: OSI Approved :: MIT License
Classifier: Operating System :: OS Independent
Requires-Python: >=3.7
License-File: LICENSE
Requires-Dist: requests
Requires-Dist: urllib3 <3,>=1.26
